wilddrummer/__init__.py
wilddrummer/utils.py
wilddrummer/wild_drummer.py
wilddrummer-0.1.0.dist-info/LICENSE
wilddrummer-0.1.0.dist-info/METADATA
wilddrummer-0.1.0.dist-info/WHEEL
wilddrummer-0.1.0.dist-info/entry_points.txt
wilddrummer-0.1.0.dist-info/top_level.txt
wilddrummer-0.1.0.dist-info/RECORD
