Metadata-Version: 2.1
Name: wilddrummer
Version: 0.1.0
Summary: Turn sound samples into drums.
Home-page: https://github.com/onebotstudio/wild-drummer
Author: OneBotStudio
License: UNKNOWN
Platform: UNKNOWN
Requires-Python: >=3.7
License-File: LICENSE
Requires-Dist: appdirs (==1.4.4)
Requires-Dist: audioread (==2.1.9)
Requires-Dist: certifi (==2021.10.8)
Requires-Dist: cffi (==1.15.0)
Requires-Dist: charset-normalizer (==2.0.7)
Requires-Dist: click (==8.0.3)
Requires-Dist: cycler (==0.11.0)
Requires-Dist: decorator (==5.1.0)
Requires-Dist: Flask (==2.0.2)
Requires-Dist: gunicorn (==20.1.0)
Requires-Dist: idna (==3.3)
Requires-Dist: itsdangerous (==2.0.1)
Requires-Dist: Jinja2 (==3.0.3)
Requires-Dist: joblib (==1.1.0)
Requires-Dist: kiwisolver (==1.3.2)
Requires-Dist: librosa (==0.8.1)
Requires-Dist: llvmlite (==0.37.0)
Requires-Dist: MarkupSafe (==2.0.1)
Requires-Dist: matplotlib (==3.4.3)
Requires-Dist: noisereduce (==2.0.0)
Requires-Dist: numba (==0.54.1)
Requires-Dist: numpy (>=1.17)
Requires-Dist: packaging (==21.2)
Requires-Dist: Pillow (==8.4.0)
Requires-Dist: pooch (==1.5.2)
Requires-Dist: pycparser (==2.21)
Requires-Dist: pydub (==0.25.1)
Requires-Dist: pyparsing (==2.4.7)
Requires-Dist: python-dateutil (==2.8.2)
Requires-Dist: requests (==2.26.0)
Requires-Dist: resampy (==0.2.2)
Requires-Dist: scikit-learn (==1.0.1)
Requires-Dist: scipy (==1.7.2)
Requires-Dist: six (==1.16.0)
Requires-Dist: SoundFile (==0.10.3.post1)
Requires-Dist: threadpoolctl (==3.0.0)
Requires-Dist: tqdm (==4.62.3)
Requires-Dist: urllib3 (==1.26.7)
Requires-Dist: Werkzeug (==2.0.2)
Provides-Extra: interactive
Requires-Dist: matplotlib ; extra == 'interactive'
